{
  "jurisdiction": "Arkansas",
  "transparency_law": "Arkansas Freedom of Information Act", 
  "legal_citation": "Arkansas Code Annotated Title 25, Chapter 19, Sections 25-19-101 through 25-19-109",
  "effective_date": "February 14, 1967 (Act 93 of 1967)",
  "research_date": "2025-09-05",
  
  "law_summary": {
    "official_name": "Arkansas Freedom of Information Act",
    "response_deadline_days": {
      "immediate_access": "During business hours if records available",
      "active_use_storage": "3 working days maximum",
      "advance_notice": "Up to 24 hours may be required for inspection",
      "attorney_general_opinion": "3 working days for personnel records"
    },
    "appeal_process": "Direct to circuit court - no administrative appeal required",
    "appeal_deadline": "No specific deadline established",
    "criminal_penalties": "Class C misdemeanor, up to $500 fine for willful violations",
    "fee_structure": "Reasonable copying fees; pre-payment required if over $25; custodian bears separation costs",
    "requester_requirements": "Arkansas citizens only",
    "key_exemptions": [
      "Income tax records",
      "Medical and adoption records", 
      "Student academic records",
      "Historical/archaeological files",
      "Grand jury minutes",
      "Ongoing criminal investigations",
      "Personnel and evaluation records",
      "Working papers of officials",
      "Competitive advantage information",
      "Library user records"
    ]
  },

  "agencies": [
    {
      "id": "AR-001",
      "name": "Office of the Governor",
      "category": "Executive",
      "description": "Chief executive office of Arkansas state government",
      "website": "https://portal.arkansas.gov/agencies/governors-office/",
      "contact_info": {
        "address": "State Capitol Building, 500 Woodlane Street, Little Rock, AR 72201",
        "phone": "(501) 682-2345",
        "public_records_contact": "Governor's Office"
      },
      "records_commonly_requested": [
        "Executive orders and proclamations",
        "Correspondence and communications",
        "Meeting calendars and schedules",
        "Budget recommendations and proposals",
        "Policy briefing materials"
      ]
    },
    
    {
      "id": "AR-002", 
      "name": "Arkansas Attorney General's Office",
      "category": "Legal/Law Enforcement",
      "description": "Legal counsel for the state and consumer protection agency",
      "website": "https://arkansasag.gov",
      "contact_info": {
        "address": "323 Center Street, Suite 200, Little Rock, AR 72201",
        "phone": "(501) 682-2007",
        "toll_free": "(800) 482-8982",
        "email": "oag@ArkansasAG.gov",
        "public_records_contact": "FOIA Coordinator"
      },
      "records_commonly_requested": [
        "Attorney General opinions",
        "Consumer protection case files",
        "Civil enforcement actions",
        "Legal interpretations of state law",
        "Settlement agreements"
      ]
    },

    {
      "id": "AR-003",
      "name": "Arkansas State Police", 
      "category": "Law Enforcement",
      "description": "State law enforcement agency providing police services and investigations",
      "website": "https://dps.arkansas.gov/law-enforcement/arkansas-state-police/",
      "contact_info": {
        "address": "One State Police Plaza Drive, Little Rock, AR 72209",
        "phone": "(501) 618-8000",
        "email": "info@asp.arkansas.gov",
        "media_email": "ASP.PIO@asp.arkansas.gov",
        "public_records_contact": "Records Section"
      },
      "records_commonly_requested": [
        "Traffic accident reports",
        "Crime statistics and UCR data",
        "Training records and policies",
        "Equipment and vehicle information",
        "Criminal investigation reports (non-exempt portions)"
      ]
    },

    {
      "id": "AR-004",
      "name": "Arkansas Department of Health", 
      "category": "Health",
      "description": "State health agency responsible for public health programs and regulation",
      "website": "https://healthy.arkansas.gov",
      "contact_info": {
        "address": "4815 W. Markham, Little Rock, AR 72205-3867",
        "phone": "(501) 661-2000",
        "toll_free": "1-800-462-0599",
        "public_records_contact": "FOIA Coordinator"
      },
      "records_commonly_requested": [
        "Restaurant and facility inspection reports",
        "Environmental health assessments", 
        "Public health program data",
        "Healthcare facility licensing records",
        "Disease surveillance statistics (aggregated)"
      ]
    },

    {
      "id": "AR-005",
      "name": "Arkansas Division of Higher Education",
      "category": "Education", 
      "description": "State agency overseeing higher education institutions and programs",
      "website": "https://adhe.edu",
      "contact_info": {
        "address": "101 E. Capitol Ave. Suite 300, Little Rock, AR 72201",
        "phone": "(501) 371-2000",
        "fax": "(501) 371-2001",
        "email": "adhe_info@adhe.edu",
        "public_records_contact": "Administrative Services"
      },
      "records_commonly_requested": [
        "College and university oversight records",
        "Student financial aid program data",
        "Higher education funding formulas",
        "Institutional accreditation information",
        "Academic program approval records"
      ]
    },

    {
      "id": "AR-006",
      "name": "Arkansas Department of Transportation",
      "category": "Transportation",
      "description": "State agency managing highways, bridges, and transportation infrastructure", 
      "website": "https://ardot.gov",
      "contact_info": {
        "phone": "(501) 569-2000",
        "public_records_contact": "Legal Department"
      },
      "records_commonly_requested": [
        "Highway construction contracts",
        "Bridge inspection reports", 
        "Traffic studies and engineering data",
        "Right-of-way acquisition documents",
        "Environmental impact assessments"
      ]
    },

    {
      "id": "AR-007",
      "name": "Arkansas Department of Corrections",
      "category": "Corrections",
      "description": "State corrections system managing prisons and rehabilitation programs",
      "website": "https://adc.arkansas.gov", 
      "contact_info": {
        "address": "6814 Princeton Pike, Pine Bluff, AR 71602",
        "phone": "(870) 267-6200",
        "public_records_contact": "Administrative Office"
      },
      "records_commonly_requested": [
        "Inmate population statistics",
        "Correctional facility policies and procedures",
        "Staff training and employment records",
        "Facility inspection and safety reports",
        "Rehabilitation program information"
      ]
    },

    {
      "id": "AR-008", 
      "name": "Arkansas Department of Human Services",
      "category": "Social Services",
      "description": "State agency providing social services, child welfare, and public assistance",
      "website": "https://humanservices.arkansas.gov",
      "contact_info": {
        "address": "700 Main Street, Little Rock, AR 72201",
        "phone": "(501) 682-1001",
        "public_records_contact": "Legal Services"
      },
      "records_commonly_requested": [
        "Child welfare policies and procedures",
        "Public assistance program guidelines",
        "Social services contracts and agreements",
        "Program statistics and outcomes data",
        "Foster care licensing information"
      ]
    },

    {
      "id": "AR-009",
      "name": "Arkansas Department of Finance and Administration",
      "category": "Revenue/Finance",
      "description": "State agency managing finances, revenue collection, and administrative services",
      "website": "https://www.dfa.arkansas.gov",
      "contact_info": {
        "address": "1509 West 7th Street, Little Rock, AR 72201",
        "phone": "(501) 682-4775",
        "public_records_contact": "Administrative Services"
      },
      "records_commonly_requested": [
        "State budget documents and financial reports",
        "Tax policy and revenue data",
        "State employee payroll information",
        "Procurement and contracting records",
        "Property assessment procedures"
      ]
    },

    {
      "id": "AR-010",
      "name": "Arkansas Department of Labor and Licensing",
      "category": "Labor/Employment",
      "description": "State agency overseeing labor standards, workplace safety, and professional licensing",
      "website": "https://www.labor.arkansas.gov",
      "contact_info": {
        "address": "10421 West Markham Street, Little Rock, AR 72205",
        "phone": "(501) 682-4500",
        "public_records_contact": "Administrative Division"
      },
      "records_commonly_requested": [
        "Workplace safety inspection reports",
        "Professional licensing records", 
        "Labor standards enforcement cases",
        "Employment statistics and data",
        "Workers' compensation information"
      ]
    },

    {
      "id": "AR-011",
      "name": "Arkansas Secretary of State",
      "category": "Elections/Business",
      "description": "State elections administration, business registration, and official records",
      "website": "https://www.sos.arkansas.gov",
      "contact_info": {
        "address": "1401 West Capitol Ave, Suite 250, Little Rock, AR 72201",
        "phone": "(501) 682-1010",
        "public_records_contact": "Administrative Office"
      },
      "records_commonly_requested": [
        "Election results and voting statistics",
        "Campaign finance reports",
        "Business entity filings and registrations",
        "Notary public records",
        "Initiative and referendum petitions"
      ]
    },

    {
      "id": "AR-012",
      "name": "Arkansas Department of Agriculture", 
      "category": "Agriculture",
      "description": "State agency overseeing agriculture, food safety, and rural development",
      "website": "https://www.agriculture.arkansas.gov",
      "contact_info": {
        "address": "#1 Natural Resources Drive, Little Rock, AR 72205",
        "phone": "(501) 683-4851",
        "public_records_contact": "Administrative Services"
      },
      "records_commonly_requested": [
        "Food safety inspection reports",
        "Agricultural commodity statistics",
        "Pesticide and fertilizer regulation records",
        "Farm program information",
        "Agricultural business licensing"
      ]
    },

    {
      "id": "AR-013",
      "name": "Arkansas Department of Energy and Environment",
      "category": "Environment", 
      "description": "State environmental protection and energy regulation agency",
      "website": "https://www.adeq.state.ar.us",
      "contact_info": {
        "address": "5301 Northshore Drive, North Little Rock, AR 72118",
        "phone": "(501) 682-0744",
        "public_records_contact": "Public Information Officer"
      },
      "records_commonly_requested": [
        "Environmental permits and violations",
        "Air and water quality monitoring data",
        "Hazardous waste facility inspections",
        "Environmental compliance enforcement",
        "Energy facility licensing records"
      ]
    },

    {
      "id": "AR-014",
      "name": "Arkansas Game and Fish Commission",
      "category": "Natural Resources",
      "description": "State agency managing fish and wildlife resources, hunting and fishing",
      "website": "https://www.agfc.com", 
      "contact_info": {
        "address": "2 Natural Resources Drive, Little Rock, AR 72205",
        "phone": "(501) 223-6300",
        "public_records_contact": "Administrative Services"
      },
      "records_commonly_requested": [
        "Wildlife population surveys and studies",
        "Hunting and fishing license statistics",
        "Habitat management and restoration projects",
        "Species conservation plans",
        "Wildlife law enforcement records"
      ]
    },

    {
      "id": "AR-015",
      "name": "Arkansas Department of Veterans Affairs",
      "category": "Veterans Services",
      "description": "State agency providing services and benefits to military veterans",
      "website": "https://www.veterans.arkansas.gov",
      "contact_info": {
        "address": "2200 Fort Roots Drive, Building 65, North Little Rock, AR 72114",
        "phone": "(501) 370-3820",
        "public_records_contact": "Administrative Office"
      },
      "records_commonly_requested": [
        "Veterans benefits program information",
        "State veterans home operations and policies",
        "Veterans cemetery records and procedures",
        "Veterans assistance program statistics",
        "Outreach and educational materials"
      ]
    }
  ],

  "request_templates": [
    {
      "template_id": "AR-STANDARD",
      "name": "Arkansas Standard FOIA Request",
      "description": "General purpose records request for Arkansas state agencies",
      "template_text": "Dear Records Custodian:\n\nPursuant to the Arkansas Freedom of Information Act, Arkansas Code Annotated §§ 25-19-101 through 25-19-109, I respectfully request access to and copies of the following public records:\n\n[SPECIFY RECORDS REQUESTED WITH SUFFICIENT DETAIL TO ENABLE CUSTODIAN TO LOCATE WITH REASONABLE EFFORT]\n\nAs an Arkansas citizen, I am entitled to inspect and copy public records during regular business hours. If these records are in active use or storage and not immediately available, please certify this fact in writing and set a date and hour within three (3) working days when the records will be available.\n\nIf it is necessary to separate exempt from non-exempt information, I understand that you will bear the cost of separation per A.C.A. § 25-19-105(e)(1).\n\nIf you determine that some portions of these records are exempt from disclosure, please provide the non-exempt portions and cite the specific statutory authority for any withholdings.\n\nRegarding fees, I understand you may charge reasonable fees for copies. If the total fees will exceed twenty-five dollars ($25.00), please notify me in advance and I will arrange for payment.\n\nIf you are not the custodian of these records, please notify me and identify the custodian if known to you.\n\nThis request may be processed [IN PERSON/BY MAIL/BY EMAIL/BY FAX] as convenient.\n\nThank you for your prompt attention to this matter.\n\nSincerely,\n[REQUESTER NAME]\n[ARKANSAS ADDRESS]\n[CITY, STATE ZIP]\n[PHONE NUMBER]\n[EMAIL ADDRESS]\n[DATE]"
    },
    
    {
      "template_id": "AR-PERSONNEL",
      "name": "Arkansas Personnel Records Request",
      "description": "Specific template for requesting one's own personnel or evaluation records",
      "template_text": "Dear Records Custodian:\n\nPursuant to Arkansas Code Annotated § 25-19-105.1, I respectfully request access to and copies of my own personnel records and evaluation records.\n\nI am requesting the following personnel/evaluation records concerning myself:\n[SPECIFY RECORDS REQUESTED]\n\nMy identifying information:\nFull Name: [FULL LEGAL NAME]\nDates of Employment: [START DATE] to [END DATE OR PRESENT]\nPosition(s) Held: [JOB TITLES]\nDepartment/Division: [WORK LOCATION]\nEmployee ID (if known): [ID NUMBER]\n\nPer A.C.A. § 25-19-105.1(c)(1), as the subject of these personnel records, I have the right to inspect, copy, and receive copies of my own personnel and evaluation records.\n\nIf you deny this request, please be advised that per A.C.A. § 25-19-105.1(c)(2), I may immediately seek an opinion from the Arkansas Attorney General, who must issue an opinion within three (3) working days stating whether your decision is consistent with Arkansas law.\n\nPlease provide these records during regular business hours or notify me when they will be available for inspection.\n\nI understand reasonable fees may apply for copying.\n\nThank you for your compliance with Arkansas transparency law.\n\nSincerely,\n[REQUESTER NAME - MUST MATCH PERSONNEL RECORDS]\n[ARKANSAS ADDRESS]\n[CITY, STATE ZIP]\n[PHONE NUMBER]\n[EMAIL ADDRESS]\n[DATE]\n\nEnclosed: [COPY OF ID OR OTHER VERIFICATION IF REQUIRED]"
    },

    {
      "template_id": "AR-COURT-APPEAL",
      "name": "Arkansas Circuit Court FOIA Appeal",
      "description": "Template for filing circuit court action for denied FOIA request",
      "template_text": "IN THE CIRCUIT COURT OF [COUNTY NAME] COUNTY, ARKANSAS\n\n[PLAINTIFF NAME],           )\n  Plaintiff,                )\n                           )\n  v.                       )  Case No. ____________\n                           )\n[DEFENDANT AGENCY/OFFICIAL], )\n  Defendant.               )\n\nCOMPLAINT FOR ENFORCEMENT OF ARKANSAS FREEDOM OF INFORMATION ACT\n\nTO THE HONORABLE COURT:\n\nPlaintiff [NAME], an Arkansas citizen, brings this action under Arkansas Code Annotated § 25-19-109 to compel compliance with the Arkansas Freedom of Information Act.\n\n1. PARTIES\nPlaintiff is an Arkansas citizen entitled to access public records under A.C.A. §§ 25-19-101 et seq.\n\nDefendant [AGENCY/OFFICIAL] is a [DESCRIBE - e.g., state agency, municipal corporation, etc.] subject to the Arkansas FOIA.\n\n2. JURISDICTION AND VENUE\nThis Court has jurisdiction under A.C.A. § 25-19-109. Venue is proper as the public records are located in [COUNTY] County.\n\n3. FACTUAL BACKGROUND\nOn [DATE], Plaintiff submitted a written FOIA request to Defendant seeking [DESCRIBE RECORDS].\n\n[On [DATE], Defendant denied the request, stating [REASON FOR DENIAL].]\n[OR: Defendant has failed to respond to the request despite [TIME PERIOD] having elapsed.]\n\n4. CLAIMS FOR RELIEF\nDefendant's denial/failure to respond violates A.C.A. § 25-19-105 because [EXPLAIN WHY DENIAL IS IMPROPER].\n\n5. REQUEST FOR RELIEF\nWHEREFORE, Plaintiff respectfully requests:\na) Order compelling production of the requested records;\nb) Declaration that Defendant violated the Arkansas FOIA;\nc) Assessment of costs, reasonable attorney's fees, and expenses per A.C.A. § 25-19-109(c) if bad faith is found;\nd) Other relief deemed just and proper.\n\nPer A.C.A. § 25-19-109(b), the burden of proving an exemption permits denial is on Defendant.\n\nRespectfully submitted,\n\n_________________________\n[ATTORNEY NAME AND BAR NUMBER]\n[OR PLAINTIFF SIGNATURE IF PRO SE]\n[ADDRESS]\n[CITY, STATE ZIP]\n[PHONE]\n[EMAIL]\nAttorney for Plaintiff [OR \"Pro Se\"]\n\nVERIFICATION\n[Include verification by plaintiff that facts are true and correct]"
    }
  ],

  "research_sources": [
    "Arkansas Code Annotated Title 25, Chapter 19, Sections 25-19-101 through 25-19-109",
    "Arkansas Attorney General FOIA Handbook (19th Edition)",
    "Arkansas Department of Public Safety FOIA guidance materials",
    "Reporters Committee for Freedom of the Press - Arkansas Open Government Guide",
    "Ballotpedia - Arkansas FOIA procedures",
    "National Freedom of Information Coalition - Arkansas FOIA Laws",
    "Encyclopedia of Arkansas - Arkansas Freedom of Information Act",
    "Arkansas state government agency websites and directories"
  ]
}